fdtd/__init__.py
fdtd/bases.py
fdtd/boundaries.py
fdtd/constants.py
fdtd/detectors.py
fdtd/exceptions.py
fdtd/field.py
fdtd/grid.py
fdtd/lumped_elements.py
fdtd/materials.py
fdtd/objects.py
fdtd/plotting.py
fdtd/pml.py
fdtd/solver.py
fdtd/sources.py
fdtd/utils.py
fdtd/waveforms.py
fdtd.py-0.0.2.dist-info/LICENSE
fdtd.py-0.0.2.dist-info/WHEEL
fdtd.py-0.0.2.dist-info/METADATA
fdtd.py-0.0.2.dist-info/RECORD
