Metadata-Version: 2.1
Name: fdtd.py
Version: 0.0.2
Summary: 
License: MIT
Author: Tiago Vilela
Author-email: tiagovla@gmail.com
Requires-Python: >=3.8,<4.0
Classifier: License :: OSI Approved :: MIT License
Classifier: Programming Language :: Python :: 3
Classifier: Programming Language :: Python :: 3.8
Classifier: Programming Language :: Python :: 3.9
Requires-Dist: matplotlib (>=3.3.3,<4.0.0)
Requires-Dist: numpy (>=1.19.5,<2.0.0)
Requires-Dist: scipy (>=1.6.1,<2.0.0)
Requires-Dist: tqdm (>=4.57.0,<5.0.0)
